pywattbox/__init__.py
pywattbox/base.py
pywattbox/driver/__init__.py
pywattbox/driver/async_driver.py
pywattbox/driver/sync_driver.py
pywattbox/http_wattbox.py
pywattbox/ip_wattbox.py
pywattbox/py.typed
pywattbox-0.9.0.dist-info/LICENSE
pywattbox-0.9.0.dist-info/METADATA
pywattbox-0.9.0.dist-info/WHEEL
pywattbox-0.9.0.dist-info/RECORD
